pysbgn/__init__.py
pysbgn/sbgn_core.py
pysbgn/sbgn_types.py
pysbgn-0.2.1.dist-info/LICENSE
pysbgn-0.2.1.dist-info/METADATA
pysbgn-0.2.1.dist-info/WHEEL
pysbgn-0.2.1.dist-info/top_level.txt
pysbgn-0.2.1.dist-info/RECORD
