Metadata-Version: 2.1
Name: pysbgn
Version: 0.2.1
Summary: Support for SBGN ML v0.3 via generateDS
Home-page: https://github.com/vpodpecan/pysbgn
Author: Vid Podpečan
Author-email: vid.podpecan@ijs.si
License: UNKNOWN
Project-URL: Bug Tracker, https://github.com/vpodpecan/pysbgn/issues
Platform: UNKNOWN
Classifier: Programming Language :: Python :: 3
Classifier: License :: OSI Approved :: MIT License
Classifier: Operating System :: OS Independent
Classifier: Topic :: Software Development :: Libraries
Requires-Python: >=3.5
License-File: LICENSE
